{ "compressionlevel":-1,
 "height":20,
 "infinite":false,
 "layers":[
        {
         "data":[0, 0, 0, 0, 0, 0, 0, 0, 0, 0, 0, 0, 0, 0, 0, 0, 0, 0, 0, 0, 0, 0, 0, 0, 0, 0, 0,
            0, 0, 0, 0, 0, 0, 0, 0, 0, 0, 0, 0, 0, 0, 0, 0, 0, 0, 0, 0, 0, 0, 0, 0, 0, 0, 0,
            0, 0, 0, 0, 0, 0, 0, 0, 0, 0, 0, 0, 0, 0, 0, 0, 0, 0, 0, 0, 0, 0, 0, 0, 0, 0, 0,
            0, 0, 0, 0, 0, 0, 0, 0, 0, 0, 0, 0, 0, 0, 0, 0, 0, 0, 0, 0, 0, 0, 0, 0, 0, 0, 0,
            0, 0, 0, 0, 0, 0, 0, 329, 329, 329, 329, 329, 329, 295, 295, 295, 295, 0, 0, 0, 0, 0, 0, 0, 0, 0, 0,
            0, 0, 0, 0, 0, 0, 0, 349, 349, 349, 349, 349, 349, 315, 315, 315, 315, 0, 0, 0, 0, 0, 0, 0, 0, 0, 0,
            0, 0, 0, 0, 0, 0, 0, 226, 227, 227, 227, 227, 227, 118, 118, 118, 118, 0, 0, 0, 0, 0, 0, 0, 0, 0, 0,
            0, 0, 0, 0, 329, 329, 329, 226, 227, 227, 227, 227, 227, 118, 118, 118, 118, 0, 0, 0, 0, 0, 0, 0, 0, 0, 0,
            0, 0, 0, 0, 349, 349, 349, 226, 227, 227, 227, 227, 227, 118, 118, 118, 118, 0, 0, 0, 0, 0, 0, 0, 0, 0, 0,
            0, 0, 0, 0, 226, 227, 227, 227, 227, 227, 227, 227, 227, 118, 118, 118, 118, 0, 0, 0, 0, 0, 0, 0, 0, 0, 0,
            0, 0, 0, 0, 239, 239, 2147483888, 227, 227, 227, 227, 227, 227, 227, 227, 227, 227, 0, 0, 0, 0, 0, 0, 0, 0, 0, 0,
            0, 0, 0, 0, 0, 0, 0, 226, 227, 227, 227, 227, 227, 227, 227, 227, 227, 0, 0, 0, 0, 0, 0, 0, 0, 0, 0,
            0, 0, 0, 0, 0, 0, 0, 226, 227, 227, 227, 227, 227, 227, 227, 227, 227, 0, 0, 0, 0, 0, 0, 0, 0, 0, 0,
            0, 0, 0, 0, 0, 0, 0, 246, 247, 247, 247, 247, 247, 247, 247, 247, 247, 0, 0, 0, 0, 0, 0, 0, 0, 0, 0,
            0, 0, 0, 0, 0, 0, 0, 0, 0, 0, 0, 0, 0, 0, 0, 0, 0, 0, 0, 0, 0, 0, 0, 0, 0, 0, 0,
            0, 0, 0, 0, 0, 0, 0, 0, 0, 0, 0, 0, 0, 0, 0, 0, 0, 0, 0, 0, 0, 0, 0, 0, 0, 0, 0,
            0, 0, 0, 0, 0, 0, 0, 0, 0, 0, 0, 0, 0, 0, 0, 0, 0, 0, 0, 0, 0, 0, 0, 0, 0, 0, 0,
            0, 0, 0, 0, 0, 0, 0, 0, 0, 0, 0, 0, 0, 0, 0, 0, 0, 0, 0, 0, 0, 0, 0, 0, 0, 0, 0,
            0, 0, 0, 0, 0, 0, 0, 0, 0, 0, 0, 0, 0, 0, 0, 0, 0, 0, 0, 0, 0, 0, 0, 0, 0, 0, 0,
            0, 0, 0, 0, 0, 0, 0, 0, 0, 0, 0, 0, 0, 0, 0, 0, 0, 0, 0, 0, 0, 0, 0, 0, 0, 0, 0],
         "height":20,
         "id":1,
         "name":"ground",
         "opacity":1,
         "type":"tilelayer",
         "visible":true,
         "width":27,
         "x":0,
         "y":0
        }, 
        {
         "data":[0, 0, 0, 0, 0, 0, 0, 0, 0, 0, 0, 0, 0, 0, 0, 0, 0, 0, 0, 0, 0, 0, 0, 0, 0, 0, 0,
            0, 0, 0, 0, 0, 0, 0, 0, 0, 0, 0, 0, 0, 0, 0, 0, 0, 0, 0, 0, 0, 0, 0, 0, 0, 0, 0,
            0, 0, 0, 0, 0, 0, 0, 0, 0, 0, 0, 0, 0, 0, 0, 0, 0, 0, 0, 0, 0, 0, 0, 0, 0, 0, 0,
            0, 0, 0, 0, 0, 0, 0, 0, 0, 0, 0, 0, 0, 0, 0, 0, 0, 0, 0, 0, 0, 0, 0, 0, 0, 0, 0,
            0, 0, 0, 0, 0, 0, 0, 0, 0, 0, 0, 0, 0, 1610612761, 0, 0, 0, 0, 0, 0, 0, 0, 0, 0, 0, 0, 0,
            0, 0, 0, 0, 0, 0, 0, 0, 0, 0, 0, 0, 0, 1610612761, 0, 0, 0, 0, 0, 0, 0, 0, 0, 0, 0, 0, 0,
            0, 0, 0, 0, 0, 0, 0, 0, 0, 0, 0, 0, 0, 1610612761, 0, 0, 0, 0, 0, 0, 0, 0, 0, 0, 0, 0, 0,
            0, 0, 0, 0, 0, 849, 0, 0, 0, 0, 0, 0, 0, 1610612761, 0, 952, 0, 0, 0, 0, 0, 0, 0, 0, 0, 0, 0,
            0, 0, 0, 0, 0, 865, 0, 0, 0, 0, 227, 227, 0, 0, 0, 968, 0, 227, 227, 227, 227, 227, 227, 228, 0, 0, 0,
            0, 0, 0, 0, 0, 0, 0, 0, 0, 227, 227, 227, 0, 1610612761, 0, 984, 0, 227, 227, 227, 227, 227, 227, 228, 0, 0, 0,
            0, 0, 0, 0, 0, 239, 0, 0, 0, 227, 227, 227, 0, 24, 25, 25, 25, 227, 227, 227, 227, 227, 227, 228, 0, 0, 0,
            0, 0, 0, 0, 0, 0, 0, 0, 0, 0, 1064, 1065, 1066, 0, 0, 0, 0, 227, 227, 227, 227, 227, 227, 228, 0, 0, 0,
            0, 0, 0, 0, 0, 0, 0, 0, 0, 0, 1080, 1081, 1082, 0, 0, 0, 0, 227, 227, 227, 227, 227, 227, 0, 0, 0, 0,
            0, 0, 0, 0, 0, 0, 0, 0, 0, 0, 0, 0, 0, 0, 0, 0, 0, 0, 0, 0, 0, 0, 0, 0, 0, 0, 0,
            0, 0, 0, 0, 0, 0, 0, 0, 0, 0, 0, 0, 0, 0, 0, 0, 0, 0, 0, 0, 0, 0, 0, 0, 0, 0, 0,
            0, 0, 0, 0, 0, 0, 0, 0, 0, 0, 0, 0, 0, 0, 0, 0, 0, 0, 0, 0, 0, 0, 0, 0, 0, 0, 0,
            0, 0, 0, 0, 0, 0, 0, 0, 0, 0, 0, 0, 0, 0, 0, 0, 0, 0, 0, 0, 0, 0, 0, 0, 0, 0, 0,
            0, 0, 0, 0, 0, 0, 0, 0, 0, 0, 0, 0, 0, 0, 0, 0, 0, 0, 0, 0, 0, 0, 0, 0, 0, 0, 0,
            0, 0, 0, 0, 0, 0, 0, 0, 0, 0, 0, 0, 0, 0, 0, 0, 0, 0, 0, 0, 0, 0, 0, 0, 0, 0, 0,
            0, 0, 0, 0, 0, 0, 0, 0, 0, 0, 0, 0, 0, 0, 0, 0, 0, 0, 0, 0, 0, 0, 0, 0, 0, 0, 0],
         "height":20,
         "id":2,
         "name":"ground-2",
         "opacity":1,
         "type":"tilelayer",
         "visible":true,
         "width":27,
         "x":0,
         "y":0
        }, 
        {
         "data":[0, 0, 0, 0, 0, 0, 0, 0, 0, 0, 0, 0, 0, 0, 0, 0, 0, 0, 0, 0, 0, 0, 0, 0, 0, 0, 0,
            0, 0, 0, 0, 0, 0, 0, 0, 0, 0, 0, 0, 0, 0, 0, 0, 0, 0, 0, 0, 0, 0, 0, 0, 0, 0, 0,
            0, 0, 0, 0, 0, 0, 0, 0, 0, 0, 0, 0, 0, 0, 0, 0, 0, 0, 0, 0, 0, 0, 0, 0, 0, 0, 0,
            0, 0, 0, 0, 0, 0, 0, 0, 0, 0, 0, 0, 0, 0, 0, 0, 0, 0, 0, 0, 0, 0, 0, 0, 0, 0, 0,
            0, 0, 0, 0, 0, 0, 0, 0, 0, 0, 0, 0, 0, 9, 0, 0, 3221225481, 0, 0, 0, 0, 0, 0, 0, 0, 0, 0,
            0, 0, 0, 0, 0, 0, 0, 0, 0, 0, 0, 0, 0, 9, 0, 0, 3221225481, 0, 0, 0, 0, 0, 0, 0, 0, 0, 0,
            0, 0, 0, 0, 0, 0, 0, 0, 0, 0, 0, 0, 0, 9, 0, 0, 3221225481, 329, 329, 329, 329, 329, 329, 329, 0, 0, 0,
            0, 0, 0, 0, 0, 0, 0, 0, 0, 0, 0, 0, 0, 9, 0, 0, 3221225481, 349, 349, 349, 349, 349, 349, 349, 0, 0, 0,
            0, 0, 0, 0, 0, 0, 0, 0, 0, 0, 0, 227, 0, 0, 0, 0, 3221225481, 0, 0, 0, 0, 0, 0, 0, 0, 0, 0,
            0, 0, 0, 0, 0, 0, 0, 0, 0, 227, 0, 227, 0, 0, 0, 0, 3221225481, 0, 0, 0, 0, 0, 0, 0, 0, 0, 0,
            0, 0, 0, 0, 0, 0, 0, 0, 0, 0, 0, 0, 0, 0, 0, 0, 3221225481, 0, 0, 850, 852, 851, 0, 0, 0, 0, 0,
            0, 0, 0, 0, 0, 0, 0, 0, 0, 0, 0, 0, 0, 0, 0, 0, 0, 0, 0, 866, 868, 867, 0, 0, 0, 0, 0,
            0, 0, 0, 0, 0, 0, 0, 0, 0, 0, 0, 0, 0, 0, 0, 0, 3221225481, 247, 247, 247, 247, 247, 247, 248, 0, 0, 0,
            0, 0, 0, 0, 0, 0, 0, 0, 0, 0, 0, 0, 0, 0, 0, 0, 3221225481, 0, 0, 0, 0, 0, 0, 0, 0, 0, 0,
            0, 0, 0, 0, 0, 0, 0, 0, 0, 0, 0, 0, 0, 0, 0, 0, 0, 0, 0, 0, 0, 0, 0, 0, 0, 0, 0,
            0, 0, 0, 0, 0, 0, 0, 0, 0, 0, 0, 0, 0, 0, 0, 0, 0, 0, 0, 0, 0, 0, 0, 0, 0, 0, 0,
            0, 0, 0, 0, 0, 0, 0, 0, 0, 0, 0, 0, 0, 0, 0, 0, 0, 0, 0, 0, 0, 0, 0, 0, 0, 0, 0,
            0, 0, 0, 0, 0, 0, 0, 0, 0, 0, 0, 0, 0, 0, 0, 0, 0, 0, 0, 0, 0, 0, 0, 0, 0, 0, 0,
            0, 0, 0, 0, 0, 0, 0, 0, 0, 0, 0, 0, 0, 0, 0, 0, 0, 0, 0, 0, 0, 0, 0, 0, 0, 0, 0,
            0, 0, 0, 0, 0, 0, 0, 0, 0, 0, 0, 0, 0, 0, 0, 0, 0, 0, 0, 0, 0, 0, 0, 0, 0, 0, 0],
         "height":20,
         "id":6,
         "name":"ground-3",
         "opacity":1,
         "type":"tilelayer",
         "visible":true,
         "width":27,
         "x":0,
         "y":0
        }, 
        {
         "data":[0, 0, 0, 0, 0, 0, 0, 0, 0, 0, 0, 0, 0, 0, 0, 0, 0, 0, 0, 0, 0, 0, 0, 0, 0, 0, 0,
            0, 0, 0, 0, 0, 0, 0, 0, 0, 0, 0, 0, 0, 0, 0, 0, 0, 0, 0, 0, 0, 0, 0, 0, 0, 0, 0,
            0, 0, 0, 0, 0, 0, 0, 0, 0, 0, 0, 0, 0, 0, 0, 0, 0, 0, 0, 0, 0, 0, 0, 0, 0, 0, 0,
            0, 0, 0, 0, 0, 0, 0, 0, 0, 0, 0, 0, 0, 0, 0, 0, 0, 0, 0, 0, 0, 0, 0, 0, 0, 0, 0,
            0, 0, 0, 0, 0, 0, 0, 0, 1456, 1457, 1540, 1541, 0, 0, 780, 781, 782, 0, 0, 0, 0, 0, 0, 0, 0, 0, 0,
            0, 0, 0, 0, 0, 0, 0, 0, 1472, 1473, 1556, 1557, 0, 0, 796, 797, 798, 0, 0, 0, 0, 0, 0, 0, 0, 0, 0,
            0, 0, 0, 0, 0, 0, 0, 0, 1488, 1489, 1572, 1573, 0, 0, 0, 0, 0, 0, 0, 0, 0, 0, 0, 0, 0, 0, 0,
            0, 0, 0, 0, 0, 0, 0, 0, 0, 0, 0, 0, 0, 0, 0, 0, 0, 0, 0, 0, 0, 0, 0, 0, 0, 0, 0,
            0, 0, 0, 0, 0, 0, 0, 0, 0, 0, 227, 227, 0, 0, 0, 523, 0, 0, 0, 0, 0, 0, 0, 0, 0, 0, 0,
            0, 0, 0, 0, 0, 227, 0, 0, 227, 227, 227, 227, 0, 0, 0, 539, 0, 0, 0, 0, 0, 0, 0, 0, 0, 0, 0,
            0, 0, 0, 0, 0, 239, 0, 0, 1681, 1682, 0, 1071, 1072, 0, 0, 0, 0, 0, 0, 0, 0, 0, 0, 981, 0, 0, 0,
            0, 0, 0, 0, 0, 0, 0, 0, 1729, 1730, 0, 0, 0, 0, 0, 0, 0, 0, 0, 0, 0, 0, 0, 997, 0, 0, 0,
            0, 0, 0, 0, 0, 0, 0, 0, 1713, 1714, 0, 0, 0, 0, 0, 0, 0, 0, 0, 0, 0, 0, 0, 0, 0, 0, 0,
            0, 0, 0, 0, 0, 0, 0, 0, 0, 0, 0, 0, 0, 0, 0, 0, 0, 0, 0, 0, 0, 0, 0, 0, 0, 0, 0,
            0, 0, 0, 0, 0, 0, 0, 0, 0, 0, 0, 0, 0, 0, 0, 0, 0, 0, 0, 0, 0, 0, 0, 0, 0, 0, 0,
            0, 0, 0, 0, 0, 0, 0, 0, 0, 0, 0, 0, 0, 0, 0, 0, 0, 0, 0, 0, 0, 0, 0, 0, 0, 0, 0,
            0, 0, 0, 0, 0, 0, 0, 0, 0, 0, 0, 0, 0, 0, 0, 0, 0, 0, 0, 0, 0, 0, 0, 0, 0, 0, 0,
            0, 0, 0, 0, 0, 0, 0, 0, 0, 0, 0, 0, 0, 0, 0, 0, 0, 0, 0, 0, 0, 0, 0, 0, 0, 0, 0,
            0, 0, 0, 0, 0, 0, 0, 0, 0, 0, 0, 0, 0, 0, 0, 0, 0, 0, 0, 0, 0, 0, 0, 0, 0, 0, 0,
            0, 0, 0, 0, 0, 0, 0, 0, 0, 0, 0, 0, 0, 0, 0, 0, 0, 0, 0, 0, 0, 0, 0, 0, 0, 0, 0],
         "height":20,
         "id":4,
         "name":"objects",
         "opacity":1,
         "type":"tilelayer",
         "visible":true,
         "width":27,
         "x":0,
         "y":0
        }, 
        {
         "data":[0, 0, 0, 0, 0, 0, 0, 0, 0, 0, 0, 0, 0, 0, 0, 0, 0, 0, 0, 0, 0, 0, 0, 0, 0, 0, 0,
            0, 0, 0, 0, 0, 0, 0, 0, 0, 0, 0, 0, 0, 0, 0, 0, 0, 0, 0, 0, 0, 0, 0, 0, 0, 0, 0,
            0, 0, 0, 0, 0, 0, 0, 0, 0, 0, 0, 0, 0, 0, 0, 0, 0, 0, 0, 0, 0, 0, 0, 0, 0, 0, 0,
            0, 0, 0, 0, 0, 0, 0, 0, 0, 0, 0, 0, 0, 0, 0, 0, 0, 0, 0, 0, 0, 0, 0, 0, 0, 0, 0,
            0, 0, 0, 0, 0, 0, 0, 0, 0, 0, 0, 0, 0, 1106, 1107, 0, 0, 0, 0, 0, 0, 0, 0, 0, 0, 0, 0,
            0, 0, 0, 0, 0, 0, 0, 0, 0, 0, 0, 0, 0, 1122, 1123, 0, 0, 0, 0, 0, 0, 0, 0, 0, 0, 0, 0,
            0, 0, 0, 0, 0, 0, 0, 0, 0, 0, 0, 0, 0, 1138, 1139, 0, 524, 1048, 1049, 0, 1283, 752, 753, 0, 0, 0, 0,
            0, 0, 0, 0, 0, 0, 0, 0, 0, 0, 0, 0, 0, 0, 0, 0, 0, 1277, 1262, 0, 1299, 768, 769, 0, 0, 0, 0,
            0, 0, 0, 0, 0, 0, 0, 0, 0, 0, 0, 0, 0, 0, 0, 0, 0, 1293, 1294, 0, 1332, 0, 0, 0, 0, 0, 0,
            0, 0, 0, 0, 0, 0, 0, 0, 0, 0, 0, 0, 0, 0, 0, 0, 0, 0, 0, 0, 0, 0, 0, 0, 0, 0, 0,
            0, 0, 0, 0, 0, 0, 0, 0, 0, 0, 0, 0, 0, 0, 64, 64, 3221225520, 0, 0, 0, 0, 0, 0, 0, 0, 0, 0,
            0, 0, 0, 0, 0, 0, 0, 0, 1300, 0, 0, 0, 0, 0, 0, 0, 0, 0, 0, 0, 0, 0, 0, 0, 0, 0, 0,
            0, 0, 0, 0, 0, 0, 0, 0, 1316, 0, 0, 0, 0, 0, 0, 0, 0, 0, 0, 0, 0, 0, 0, 0, 0, 0, 0,
            0, 0, 0, 0, 0, 0, 0, 0, 1332, 0, 0, 0, 0, 0, 0, 0, 0, 0, 0, 0, 0, 0, 0, 0, 0, 0, 0,
            0, 0, 0, 0, 0, 0, 0, 0, 0, 0, 0, 0, 0, 0, 0, 0, 0, 0, 0, 0, 0, 0, 0, 0, 0, 0, 0,
            0, 0, 0, 0, 0, 0, 0, 0, 0, 0, 0, 0, 0, 0, 0, 0, 0, 0, 0, 0, 0, 0, 0, 0, 0, 0, 0,
            0, 0, 0, 0, 0, 0, 0, 0, 0, 0, 0, 0, 0, 0, 0, 0, 0, 0, 0, 0, 0, 0, 0, 0, 0, 0, 0,
            0, 0, 0, 0, 0, 0, 0, 0, 0, 0, 0, 0, 0, 0, 0, 0, 0, 0, 0, 0, 0, 0, 0, 0, 0, 0, 0,
            0, 0, 0, 0, 0, 0, 0, 0, 0, 0, 0, 0, 0, 0, 0, 0, 0, 0, 0, 0, 0, 0, 0, 0, 0, 0, 0,
            0, 0, 0, 0, 0, 0, 0, 0, 0, 0, 0, 0, 0, 0, 0, 0, 0, 0, 0, 0, 0, 0, 0, 0, 0, 0, 0],
         "height":20,
         "id":5,
         "name":"objects-2",
         "opacity":1,
         "type":"tilelayer",
         "visible":true,
         "width":27,
         "x":0,
         "y":0
        }, 
        {
         "draworder":"topdown",
         "id":7,
         "name":"boundaries",
         "objects":[
                {
                 "height":48.9001821065333,
                 "id":5,
                 "name":"sofa",
                 "polygon":[
                        {
                         "x":0.22529644268775,
                         "y":-0.558921848371392
                        }, 
                        {
                         "x":9.19477097209978,
                         "y":-0.724254509025959
                        }, 
                        {
                         "x":9.75693334329355,
                         "y":5.49440323078231
                        }, 
                        {
                         "x":22.4756258234519,
                         "y":5.71774061997054
                        }, 
                        {
                         "x":23.3333333333333,
                         "y":48.9001821065333
                        }, 
                        {
                         "x":0,
                         "y":48.9001821065333
                        }],
                 "rotation":0,
                 "type":"",
                 "visible":true,
                 "width":23.3333333333333,
                 "x":128.333333333333,
                 "y":166.766484560133
                }, 
                {
                 "height":29.6666666666667,
                 "id":6,
                 "name":"mirror",
                 "rotation":0,
                 "type":"",
                 "visible":true,
                 "width":18.3333333333333,
                 "x":134.666666666667,
                 "y":71.3333333333333
                }, 
                {
                 "height":30.3333333333333,
                 "id":8,
                 "name":"bookcase",
                 "rotation":0,
                 "type":"",
                 "visible":true,
                 "width":32,
                 "x":160,
                 "y":71
                }, 
                {
                 "height":31.3333333333333,
                 "id":9,
                 "name":"pc",
                 "rotation":0,
                 "type":"",
                 "visible":true,
                 "width":18,
                 "x":238.333333333333,
                 "y":124.666666666667
                }, 
                {
                 "height":30.3333333333333,
                 "id":11,
                 "name":"window",
                 "rotation":0,
                 "type":"",
                 "visible":true,
                 "width":31,
                 "x":231,
                 "y":70.6666666666667
                }, 
                {
                 "height":19.6666666666667,
                 "id":14,
                 "name":"docs",
                 "rotation":0,
                 "type":"",
                 "visible":true,
                 "width":30.6666666666667,
                 "x":272.666666666667,
                 "y":117.333333333333
                }, 
                {
                 "height":23.3333333333333,
                 "id":16,
                 "name":"globus",
                 "rotation":0,
                 "type":"",
                 "visible":true,
                 "width":14.3333333333333,
                 "x":367.333333333333,
                 "y":159.333333333333
                }, 
                {
                 "height":27,
                 "id":18,
                 "name":"picture",
                 "rotation":0,
                 "type":"",
                 "visible":true,
                 "width":27,
                 "x":338.666666666667,
                 "y":105.666666666667
                }, 
                {
                 "height":33,
                 "id":19,
                 "name":"",
                 "rotation":0,
                 "type":"",
                 "visible":true,
                 "width":14.3333333333334,
                 "x":319.666666666667,
                 "y":103.666666666667
                }, 
                {
                 "height":3,
                 "id":20,
                 "name":"",
                 "rotation":0,
                 "type":"",
                 "visible":true,
                 "width":2.66666666666669,
                 "x":273.333333333333,
                 "y":96
                }, 
                {
                 "height":7.66666666666667,
                 "id":23,
                 "name":"",
                 "rotation":0,
                 "type":"",
                 "visible":true,
                 "width":110.666666666667,
                 "x":271.666666666667,
                 "y":118.333333333333
                }, 
                {
                 "height":77.6666666666667,
                 "id":24,
                 "name":"",
                 "rotation":0,
                 "type":"",
                 "visible":true,
                 "width":8,
                 "x":382.333333333333,
                 "y":129.333333333333
                }, 
                {
                 "height":13.4545454545454,
                 "id":26,
                 "name":"",
                 "rotation":0,
                 "type":"",
                 "visible":true,
                 "width":8.72727272727269,
                 "x":381.909090909091,
                 "y":119.363636363636
                }, 
                {
                 "height":13,
                 "id":27,
                 "name":"",
                 "rotation":0,
                 "type":"",
                 "visible":true,
                 "width":112.375,
                 "x":271.625,
                 "y":206
                }, 
                {
                 "height":31.625,
                 "id":28,
                 "name":"",
                 "rotation":0,
                 "type":"",
                 "visible":true,
                 "width":6.625,
                 "x":264.75,
                 "y":192.75
                }, 
                {
                 "height":18.3636363636364,
                 "id":29,
                 "name":"",
                 "rotation":0,
                 "type":"",
                 "visible":true,
                 "width":152.363636363636,
                 "x":113.272727272727,
                 "y":222.909090909091
                }, 
                {
                 "height":64.7272727272727,
                 "id":30,
                 "name":"",
                 "rotation":0,
                 "type":"",
                 "visible":true,
                 "width":16.1818181818182,
                 "x":97.4545454545455,
                 "y":175.272727272727
                }, 
                {
                 "height":11.6363636363636,
                 "id":31,
                 "name":"",
                 "rotation":0,
                 "type":"",
                 "visible":true,
                 "width":47.2727272727273,
                 "x":64.3636363636364,
                 "y":175.636363636364
                }, 
                {
                 "height":34.5454545454546,
                 "id":32,
                 "name":"",
                 "rotation":0,
                 "type":"",
                 "visible":true,
                 "width":18.5454545454545,
                 "x":45.4545454545455,
                 "y":142.727272727273
                }, 
                {
                 "height":30,
                 "id":33,
                 "name":"",
                 "rotation":0,
                 "type":"",
                 "visible":true,
                 "width":47.4545454545455,
                 "x":64.7272727272727,
                 "y":112.363636363636
                }, 
                {
                 "height":46.7272727272727,
                 "id":34,
                 "name":"",
                 "rotation":0,
                 "type":"",
                 "visible":true,
                 "width":13.6363636363636,
                 "x":98,
                 "y":64.9090909090909
                }, 
                {
                 "height":9.27272727272727,
                 "id":35,
                 "name":"",
                 "rotation":0,
                 "type":"",
                 "visible":true,
                 "width":95.2727272727273,
                 "x":112.363636363636,
                 "y":85.2727272727273
                }, 
                {
                 "height":33.4545454545455,
                 "id":36,
                 "name":"",
                 "rotation":0,
                 "type":"",
                 "visible":true,
                 "width":7.09090909090909,
                 "x":207.818181818182,
                 "y":94.3636363636364
                }, 
                {
                 "height":29.8181818181818,
                 "id":37,
                 "name":"tree",
                 "rotation":0,
                 "type":"",
                 "visible":true,
                 "width":13.6363636363637,
                 "x":217.818181818182,
                 "y":72.9090909090909
                }, 
                {
                 "height":3.45454545454545,
                 "id":38,
                 "name":"",
                 "rotation":0,
                 "type":"",
                 "visible":true,
                 "width":54.7272727272727,
                 "x":210.545454545455,
                 "y":92.9090909090909
                }, 
                {
                 "height":82.7272727272727,
                 "id":39,
                 "name":"",
                 "rotation":0,
                 "type":"",
                 "visible":true,
                 "width":6.18181818181819,
                 "x":265.636363636364,
                 "y":93.0909090909091
                }, 
                {
                 "height":5.81818181818181,
                 "id":40,
                 "name":"",
                 "rotation":0,
                 "type":"",
                 "visible":true,
                 "width":57.4545454545454,
                 "x":208,
                 "y":159.636363636364
                },
            
                {
                 "height":16.1818181818182,
                 "id":41,
                 "name":"",
                 "rotation":0,
                 "type":"",
                 "visible":true,
                 "width":5.81818181818181,
                 "x":208,
                 "y":144.727272727273
                }, 
                {
                 "height":28.75,
                 "id":43,
                 "name":"exit",
                 "rotation":0,
                 "type":"",
                 "visible":true,
                 "width":14.75,
                 "x":65.25,
                 "y":144.583333333333
                }],
         "opacity":1,
         "type":"objectgroup",
         "visible":true,
         "x":0,
         "y":0
        }, 
        {
         "draworder":"topdown",
         "id":8,
         "name":"spawnpoint",
         "objects":[
                {
                 "height":0,
                 "id":44,
                 "name":"player",
                 "point":true,
                 "rotation":0,
                 "type":"",
                 "visible":true,
                 "width":0,
                 "x":100.583333333333,
                 "y":157
                }],
         "opacity":1,
         "type":"objectgroup",
         "visible":true,
         "x":0,
         "y":0
        }],
 "nextlayerid":9,
 "nextobjectid":49,
 "orientation":"orthogonal",
 "renderorder":"right-down",
 "tiledversion":"1.10.2",
 "tileheight":16,
 "tilesets":[
        {
         "firstgid":1,
         "source":"Room_Builder_free_16x16.tsj"
        }, 
        {
         "firstgid":392,
         "source":"Interiors_free_16x16.tsj"
        }],
 "tilewidth":16,
 "type":"map",
 "version":"1.10",
 "width":27
}